eventdisplay_ml/__init__.py
eventdisplay_ml/_version.py
eventdisplay_ml/config.py
eventdisplay_ml/data_processing.py
eventdisplay_ml/evaluate.py
eventdisplay_ml/features.py
eventdisplay_ml/geomag.py
eventdisplay_ml/hyper_parameters.py
eventdisplay_ml/models.py
eventdisplay_ml/utils.py
eventdisplay_ml/scripts/apply_xgb_classify.py
eventdisplay_ml/scripts/apply_xgb_stereo.py
eventdisplay_ml/scripts/plot_classification_gamma_efficiency.py
eventdisplay_ml/scripts/plot_classification_performance_metrics.py
eventdisplay_ml/scripts/train_xgb_classify.py
eventdisplay_ml/scripts/train_xgb_stereo.py
eventdisplay_ml-0.5.0.dist-info/licenses/LICENSE
eventdisplay_ml-0.5.0.dist-info/METADATA
eventdisplay_ml-0.5.0.dist-info/WHEEL
eventdisplay_ml-0.5.0.dist-info/entry_points.txt
eventdisplay_ml-0.5.0.dist-info/top_level.txt
eventdisplay_ml-0.5.0.dist-info/RECORD
