Metadata-Version: 2.4
Name: eventdisplay-ml
Version: 0.5.0
Summary: A machine learning toolkit for Eventdisplay
Author-email: Gernot Maier <gernot.maier@desy.de>
License-Expression: BSD-3-Clause
Project-URL: bug tracker, https://github.com/Eventdisplay/Eventdisplay-ML/issues
Project-URL: documentation, https://github.com/Eventdisplay/Eventdisplay-ML
Project-URL: repository, https://github.com/Eventdisplay/Eventdisplay-ML
Classifier: Intended Audience :: Science/Research
Classifier: Operating System :: OS Independent
Classifier: Programming Language :: Python :: 3 :: Only
Classifier: Programming Language :: Python :: 3.12
Classifier: Programming Language :: Python :: 3.13
Classifier: Programming Language :: Python :: 3.14
Classifier: Topic :: Scientific/Engineering :: Astronomy
Requires-Python: >=3.12
License-File: LICENSE
Requires-Dist: awkward
Requires-Dist: awkward-pandas
Requires-Dist: joblib
Requires-Dist: matplotlib
Requires-Dist: numpy
Requires-Dist: pandas
Requires-Dist: scikit-learn
Requires-Dist: scipy
Requires-Dist: tabulate
Requires-Dist: uproot
Requires-Dist: xgboost
Provides-Extra: dev
Requires-Dist: pre-commit; extra == "dev"
Requires-Dist: pylint; extra == "dev"
Requires-Dist: ruff; extra == "dev"
Requires-Dist: shellcheck; extra == "dev"
Requires-Dist: towncrier; extra == "dev"
Provides-Extra: tests
Requires-Dist: pytest; extra == "tests"
Requires-Dist: pytest-cov; extra == "tests"
Requires-Dist: pytest-mock; extra == "tests"
Requires-Dist: pytest-profiling; extra == "tests"
Requires-Dist: pytest-random-order; extra == "tests"
Requires-Dist: pytest-repeat; extra == "tests"
Requires-Dist: pytest-retry; extra == "tests"
Requires-Dist: pytest-xdist; extra == "tests"
Dynamic: license-file
